<?xml version="1.0"?>
<pagescount>
	<html_total>5</html_total>
	<html_done>5</html_done>
	<images>32</images>
	<script>3</script>
	<css>3</css>
	<pdf/>
	<documents/>
	<excel/>
	<powerpoint/>
	<flash/>
	<audios/>
	<videos/>
	<xml/>
	<json/>
	<txt/>
	<autocad/>
	<model_3d/>
	<fonts/>
	<scraping_reload>1</scraping_reload>
	<is_pretty_url>false</is_pretty_url>
	<has_trailing_slash>false</has_trailing_slash>
	<is_ebn>false</is_ebn>
	<email>thiruad@gmail.com</email>
	<theme_name>9vr6zicnazd97redcdpiq295981</theme_name>
	<server_url_front_page>http://www4.waybackmachinedownloader.com/scraping/files/live/kdsjesustravels.com_thiruad_gmail.com_3utwe7z2do/</server_url_front_page>
	<no_www_url>kdsjesustravels.com</no_www_url>
	<hosted_domain/>
	<original_archive_url>https://web.archive.org/web/20170626185757/http://www.kdsjesustravels.com/index.html</original_archive_url>
	<final_archive_url>https://web.archive.org/web/20170626185757/http://www.kdsjesustravels.com/index.html</final_archive_url>
	<front_page_code_date>20170626185757</front_page_code_date>
	<total_urls_from_api/>
	<max_reached_live>false</max_reached_live>
	<scrape_other_captures>search_ended</scrape_other_captures>
	<total_size>2928</total_size>
</pagescount>
